alphaware
