Metadata-Version: 1.1
Name: alphaware
Version: 0.2.6
Summary: alpha research tools
Home-page: https://github.com/iLampard/alphaware
Author: iLampard, RoxanneYang, MarkSh714
Author-email: UNKNOWN
License: UNKNOWN
Platform: UNKNOWN
Classifier: Programming Language :: Python
Classifier: Programming Language :: Python :: 2.7
Classifier: Programming Language :: Python :: 3.5
